barproc/__init__.py
barproc-0.0.0.dist-info/METADATA
barproc-0.0.0.dist-info/WHEEL
barproc-0.0.0.dist-info/licenses/LICENSE.txt
barproc-0.0.0.dist-info/RECORD
