Metadata-Version: 2.3
Name: barproc
Version: 0.0.0
Summary: Bar Data Processing Utilities
Author-email: Furechan <furechan@xsmail.com>
Keywords: utility
Classifier: Development Status :: 1 - Planning
Classifier: License :: OSI Approved :: MIT License
Classifier: Operating System :: OS Independent
Classifier: Programming Language :: Python :: 3
Requires-Python: >=3.8
